tableextractions/__init__.py
tableextractions/pdf_table_extractions.py
tableextractions/utils.py
cosmostables-0.19.dist-info/METADATA
cosmostables-0.19.dist-info/WHEEL
cosmostables-0.19.dist-info/top_level.txt
cosmostables-0.19.dist-info/RECORD
