Metadata-Version: 2.1
Name: cosmostables
Version: 0.19
Summary: Table extractions for COSMOS
Home-page: https://github.com/UW-COSMOS/Cosmos/tree/v0.2.0/services/table_extractions
Author: UW-COSMOS
Author-email: UNKNOWN
License: Apache
Platform: UNKNOWN
